[{"Key":"GAME_NAME","en-gb":"Pushy Paddles","it":"Pushy Paddles","es":"Pushy Paddles","el":"Pushy Paddles"},
{"Key":"BUTTON_CONNECT","en-gb":"Connect","it":"XXXX","es":"Conectar","el":"Σύνδεση"},
{"Key":"BUTTON_SERVER","en-gb":"Start Server","it":"XXXX","es":"Iniciar Servidor","el":"Εκκίνηση Διακομιστή"},
{"Key":"BUTTON_QUIT","en-gb":"Quit Game","it":"XXXX","es":"Salir del juego","el":"Κλείσιμο Παιγνιδιού"},
{"Key":"BUTTON_QUIT_TO_MENU","en-gb":"Quit To Menu","it":"XXXX","es":"Volver al menú","el":"Έξοδος στο Μενού"},
{"Key":"BUTTON_CONTINUE","en-gb":"Continue","it":"XXXX","es":"Continuar","el":"Συνέχεια"},
{"Key":"BUTTON_MENU","en-gb":"Menu","it":"XXXX","es":"Menú","el":"Μενού"},
{"Key":"BUTTON_PLAY","en-gb":"Play","it":"XXXX","es":"Jugar","el":"Παίξτε"},
{"Key":"BUTTON_PLAY_AGAIN","en-gb":"Play Again","it":"XXXX","es":"Jugar otra vez","el":"Ξαναπαίξτε"},
{"Key":"BUTTON_PAUSE","en-gb":"Pause","it":"XXXX","es":"Pausar","el":"Παύση"},
{"Key":"BUTTON_PREVIOUS","en-gb":"Previous","it":"XXXX","es":"Anterior","el":"Προηγούμενο"},
{"Key":"BUTTON_NEXT","en-gb":"Next","it":"XXXX","es":"Siguiente","el":"Επόμενο"},
{"Key":"BUTTON_SELECT","en-gb":"Select","it":"XXXX","es":"Seleccionar","el":"Επιλογή"},
{"Key":"BUTTON_CANCEL","en-gb":"Cancel","it":"XXXX","es":"Cancelar","el":"Ακύρωση"},
{"Key":"UI_MAIN_TITLE","en-gb":"Main Menu","it":"XXXX","es":"Menú principal","el":"Κεντρικό Μενού"},
{"Key":"UI_MAIN_IP_ADDRESS","en-gb":"ip address","it":"XXXX","es":"Dirección IP","el":"διεύθυνση IP"},
{"Key":"UI_MAIN_PORT","en-gb":"port","it":"XXXX","es":"Puerto","el":"θύρα"},
{"Key":"UI_MAIN_LOADING","en-gb":"Loading","it":"XXXX","es":"Cargando","el":"Φόρτωση"},
{"Key":"UI_MAIN_CONNECTING","en-gb":"Connecting","it":"XXXX","es":"Conectando","el":"Σύνδεση"},
{"Key":"UI_END_TITLE","en-gb":"Game Over","it":"XXXX","es":"Fin del juego","el":"Τέλος Παιγνιδιού"},
{"Key":"UI_END_TIME_UP","en-gb":"Time Up","it":"XXXX","es":"Tiempo agotado","el":"Τέλος Χρόνου"},
{"Key":"UI_END_ROUNDS_COMPLETED","en-gb":"Rounds Completed","it":"XXXX","es":"Rondas completadas","el":"Ολοκλήρωση Γύρου"},
{"Key":"UI_REWARDS_TITLE","en-gb":"Level Complete - Distribute Rewards","it":"XXXX","es":"Nivel completado - Distribuir recompensas","el":"Το επίπεδο ολοκληρώθηκε. Μοίρασε τις Ανταμοιβές!"},
{"Key":"UI_REWARDS_SPEED_BOOST","en-gb":"Speed Boost","it":"XXXX","es":"Aumentar velocidad","el":"Ενίσχυση Ταχύτητας"},
{"Key":"UI_REWARDS_NO_REWARD","en-gb":"No Reward","it":"XXXX","es":"Sin recompensa","el":"Καμιά Ανταμοιβή"},
{"Key":"UI_REWARDS_REVERSE_CONTROLS","en-gb":"Reverse Controls","it":"XXXX","es":"Invertir controles","el":"Αντιστροφή Πλήκτρων"},
{"Key":"UI_REWARDS_STRONGER_PUSH","en-gb":"Stronger Push","it":"XXXX","es":"Propulsión","el":"Ισχυρότερη Ώθηση"},
{"Key":"UI_REWARDS_MORE_PLATFORM_CONTROL","en-gb":"More Raft Control","it":"XXXX","es":"Más control","el":"Μεγαλύτερος Έλεγχος Πλατφόρμας"},
{"Key":"UI_CHARACTER_TITLE","en-gb":"Select a Character","it":"XXXX","es":"Selecciona un personaje","el":"Επιλογή Χαρακτήρα"},
{"Key":"UI_GAME_TOTAL","en-gb":"Total","it":"XXXX","es":"Total","el":"Σύνολο"},
{"Key":"UI_GAME_VICTORY","en-gb":"You Win","it":"XXXX","es":"Tu ganas","el":"Νικήσατε"},
{"Key":"UI_GAME_TRY_AGAIN","en-gb":"Try Again","it":"XXXX","es":"Inténtalo de nuevo","el":"Προσπαθήστε Ξανά"},
{"Key":"UI_GAME_OBJECTIVE","en-gb":"Work together to get from the bridge to the chest","it":"XXXX","es":"Trabajad juntos para dirigiros del puente al cofre","el":"Συνεργαστείτε για να φτάσετε από την γέφυρα στο σεντούκι"},
{"Key":"UI_GAME_ROUND","en-gb":"Round","it":"XXXX","es":"Partida","el":"Γύρος"},
{"Key":"UI_GAME_PLAYER","en-gb":"Player","it":"XXXX","es":"Jugador","el":"Παίκτης"},
{"Key":"UI_GAME_SERVER","en-gb":"Server","it":"XXXX","es":"Servidor","el":"Διακομιστής"},
{"Key":"UI_GAME_PAUSED","en-gb":"Game Paused","it":"XXXX","es":"Juego en pausa","el":"Παύση Παιγνιδιού"},
{"Key":"UI_GAME_TARGET","en-gb":"Target","it":"XXXX","es":"Objetivo","el":"Στόχος"},
{"Key":"UI_GAME_WAITING_FOR_PLAYERS","en-gb":"Waiting for other players…","it":"XXXX","es":"Esperando a otros jugadores...","el":"Περιμένουμε τους άλλους παίκτες..."},
{"Key":"FORMATTED_UI_END_ROUNDS_COMPLETED","en-gb":"Rounds Completed: {0}","it":"XXXX","es":"Partidas completadas","el":"Έχουν ολοκληρωθεί {0} γύροι"},
{"Key":"FORMATTED_UI_GAME_ROUND","en-gb":"Round: {0}","it":"XXXX","es":"Partida: {0}","el":"Γύρος: {0}"},
{"Key":"FORMATTED_UI_GAME_PLAYER","en-gb":"Player {0}","it":"XXXX","es":"Jugador: {0}","el":"Παίκτης {0}"},
{"Key":"FORMATTED_UI_GAME_TARGET","en-gb":"Target: {0}","it":"XXXX","es":"Objetivo: {0}","el":"Στόχος: {0}"},
{"Key":"FORMATTED_UI_GAME_CURRENT","en-gb":"Current Total: {0}","it":"XXXX","es":"Total actual: {0}","el":"Σύνολο ως τώρα: {0}"},
{"Key":"UI_INSTRUCTION_OBSTACLE_TITLE","en-gb":"Obstacle version","it":"XXXX","es":"Versión de obstáculos","el":"Έκδοση Παιγνιδιού με Εμπόδια"},
{"Key":"UI_INSTRUCTION_OBSTACLE_DESCRIPTION_A","en-gb":"Player B and C must help player A reach the finish point whilst avoiding obstacles.","it":"XXXX","es":"Los jugadores B y C deben ayudar al jugador A a llegar a la meta salvando los obstáculos","el":"Οι παίκτες B και C πρέπει να βοηθήσουν τον παίκτη A να φτάσει στον προορισμό του αποφεύγοντας τα εμπόδια."},
{"Key":"UI_INSTRUCTION_OBSTACLE_DESCRIPTION_B","en-gb":"At the end of each round player A can select upgrades for the other two players.","it":"XXXX","es":"Al final de cada ronda el jugador A puede seleccionar mejoras para los otros dos jugadores","el":"Στο τέλος κάθε γύρου ο παίκτης Α, μπορεί να διαλέξει ανταμοιβές αναβάθμισης για τους άλλους δύο παίκτες."},
{"Key":"UI_INSTRUCTION_OBSTACLE_DESCRIPTION_C","en-gb":"Players swap places after each round.","it":"XXXX","es":"Los jugadores se intercambian de posición en cada ronda","el":"Οι παίκτες αλλάζουν θέση σε κάθε γύρο."},
{"Key":"UI_INSTRUCTION_MATHS_TITLE","en-gb":"Maths version","it":"XXXX","es":"Versión de matemáticas","el":"Έκδοση Παιγνιδιού με Μαθηματικά"},
{"Key":"UI_INSTRUCTION_MATHS_DESCRIPTION_A","en-gb":"Players B and C must help player A reach the finish point by guiding the raft through the correct calculations.","it":"XXXX","es":"Los jugadores B y C deben ayudar al jugador A a llegar a la meta guiando la balsa hacia el resultado correcto","el":"Οι παίκτες B και C πρέπει να βοηθήσουν τον παίκτη A να φτάσει στον προορισμό του κατευθύνοντας τη σχεδία του με τους σωστούς υπολογισμούς."},
{"Key":"UI_INSTRUCTION_MATHS_DESCRIPTION_B","en-gb":"At end of each round player A can select upgrades for the other two players.","it":"XXXX","es":"Al final de cada ronda el jugador A puede seleccionar mejoras para los otros dos jugadores","el":"Στο τέλος κάθε γύρου ο παίκτης Α, μπορεί να διαλέξει ανταμοιβές αναβάθμισης για τους άλλους δύο παίκτες."},
{"Key":"UI_INSTRUCTION_MATHS_DESCRIPTION_C","en-gb":"Pushy Paddles Numeracy challenges 3 players to work together, solving mathematical equations through effective communication and cooperation.","it":"XXXX","es":"Pushy Paddles Numeracy reta a tres jugadores a trabajar juntos resolviendo problemas matemáticos a través de la comunicación y la cooperación","el":"Το παιγνίδι Αριθμητικής Plushy Paddles, δημιουργεί για τους τρεις παίκτες την πρόκληση να συνεργαστούν και να επικοινωνήσουν αποτελεσματικά για την επίλυση μαθηματικών εξισώσεων."}]